charabia_py-0.1.0.dist-info/METADATA
charabia_py-0.1.0.dist-info/WHEEL
charabia_py-0.1.0.dist-info/licenses/LICENSE
charabia_py/__init__.py
charabia_py/charabia_py.pypy311-pp73-x86_64-linux-gnu.so
charabia_py-0.1.0.dist-info/RECORD
